docs/CHANGELOG.md
rrtv_httprunner/__init__.py
rrtv_httprunner/__main__.py
rrtv_httprunner/app/__init__.py
rrtv_httprunner/app/main.py
rrtv_httprunner/app/routers/__init__.py
rrtv_httprunner/app/routers/debug.py
rrtv_httprunner/app/routers/debugtalk.py
rrtv_httprunner/app/routers/deps.py
rrtv_httprunner/app/routers/utils.py
rrtv_httprunner/builtin/__init__.py
rrtv_httprunner/builtin/comparators.py
rrtv_httprunner/builtin/functions.py
rrtv_httprunner/cli.py
rrtv_httprunner/client.py
rrtv_httprunner/compat.py
rrtv_httprunner/es.py
rrtv_httprunner/exceptions.py
rrtv_httprunner/ext/__init__.py
rrtv_httprunner/ext/har2case/__init__.py
rrtv_httprunner/ext/har2case/core.py
rrtv_httprunner/ext/har2case/utils.py
rrtv_httprunner/ext/locust/__init__.py
rrtv_httprunner/ext/locust/locustfile.py
rrtv_httprunner/ext/uploader/__init__.py
rrtv_httprunner/globalvar.py
rrtv_httprunner/loader.py
rrtv_httprunner/make.py
rrtv_httprunner/models.py
rrtv_httprunner/mongo.py
rrtv_httprunner/mysqls.py
rrtv_httprunner/parser.py
rrtv_httprunner/rediss.py
rrtv_httprunner/response.py
rrtv_httprunner/runner.py
rrtv_httprunner/scaffold.py
rrtv_httprunner/testcase.py
rrtv_httprunner/utils.py
rrtv_httprunner-2.8.13.dist-info/entry_points.txt
rrtv_httprunner-2.8.13.dist-info/LICENSE
rrtv_httprunner-2.8.13.dist-info/WHEEL
rrtv_httprunner-2.8.13.dist-info/METADATA
rrtv_httprunner-2.8.13.dist-info/RECORD
